sla/__init__.py
sla/classifier.py
sla/cloud_shadow_mask.py
sla/hill_shadow.py
sla/main_patches.py
sla/prep.py
sla/settings.py
sla/utils.py
sla_sca-0.1.0.dist-info/LICENSE
sla_sca-0.1.0.dist-info/WHEEL
sla_sca-0.1.0.dist-info/METADATA
sla_sca-0.1.0.dist-info/RECORD
