Metadata-Version: 2.1
Name: sla-sca
Version: 0.1.0
Summary: Snow Line Altitude (SLA) monitoring for glaciers in Argentina.
Author: Gurupratap Matharu
Author-email: gurupratap.matharu@gmail.com
Requires-Python: >=3.9,<4.0
Classifier: Programming Language :: Python :: 3
Classifier: Programming Language :: Python :: 3.10
Classifier: Programming Language :: Python :: 3.9
Requires-Dist: black (>=22.6.0,<23.0.0)
Requires-Dist: earthengine-api (>=0.1.316,<0.2.0)
Requires-Dist: geemap (>=0.15.4,<0.16.0)
Requires-Dist: ipython (>=8.4.0,<9.0.0)
Requires-Dist: sphinx (>=5.3.0,<6.0.0)
Requires-Dist: typing-extensions (>=4.3.0,<5.0.0)
